cot/__init__.py
cot/config.py
cot/train.py
cot/transfer.py
cot/utils.py
cot/data/__init__.py
cot/data/data_processing.py
cot/evals/__init__.py
cot/evals/cot.py
cot/evals/io.py
cot/models/__init__.py
cot/models/mlp.py
cot/models/transformer.py
cot/models/utils.py
metapal-0.0.0.dist-info/LICENSE.md
metapal-0.0.0.dist-info/METADATA
metapal-0.0.0.dist-info/WHEEL
metapal-0.0.0.dist-info/top_level.txt
metapal-0.0.0.dist-info/RECORD
