Metadata-Version: 2.1
Name: metapal
Version: 0.0.0
Summary: Experiments regarding LLM components
Author-email: Vivien Cabannes <vivien.cabannes@gmail.com>
Project-URL: Homepage, https://github.com/facebookresearch/pal
Project-URL: Bug Tracker, https://github.com/facebookresearch/pal/issues
Classifier: Programming Language :: Python :: 3
Classifier: License :: OSI Approved :: MIT License
Classifier: Operating System :: OS Independent
Requires-Python: >=3.9
License-File: LICENSE.md
Requires-Dist: numpy
Requires-Dist: torch
Requires-Dist: fire
Requires-Dist: sentencepiece
Requires-Dist: tiktoken
Requires-Dist: transformers
Requires-Dist: ipykernel
Requires-Dist: ipywidgets
Requires-Dist: matplotlib
Requires-Dist: networkx
Requires-Dist: black
Requires-Dist: flake8
Requires-Dist: flake8-pyproject
Requires-Dist: isort
